<?xml version="1.0" encoding="UTF-8"?><record_update sys_domain="global" table="sys_cb_topic">
    <sys_cb_topic action="DELETE">
        <applicability/>
        <applicability_mode>query</applicability_mode>
        <autopilot_topic>false</autopilot_topic>
        <category/>
        <channels/>
        <connect_queue/>
        <context_profiles/>
        <description/>
        <dialog_acts_enabled>false</dialog_acts_enabled>
        <expose_on_palette>false</expose_on_palette>
        <flexible_conversation_switching>false</flexible_conversation_switching>
        <foundational>false</foundational>
        <graph>{"graph_api_version":"1.0.68","variables":{"12a34d5f07964f90b41659dde94a41c6":{"category":"vaInputs","id":"12a34d5f07964f90b41659dde94a41c6","label":"User","name":"user","table":"sys_user","varType":"reference"},"207fa3bea5a344e2a2e017410c3da0fa":{"id":"207fa3bea5a344e2a2e017410c3da0fa","name":"needit_type","label":"NeedIt Type","varType":"choice","choices":[{"label":"legal","value":"legal"},{"label":"Facilities","value":"Facilities"},{"label":"Human Resources","value":"Human Resources","checked":true,"meta":{}}],"category":"vaInputs","nodeId":"a1513f4fd70c45d698a72c5f3fc60460","isHidden":false},"6f8c634cd0fb45f180a0b830a3956a69":{"id":"6f8c634cd0fb45f180a0b830a3956a69","name":"needit_list","label":"NeedIt List","varType":"reference","table":"x_58872_needit_needit","category":"vaInputs","nodeId":"6f4194845229447497a7d02e1ccb5ab5","isHidden":false},"70e745fa514a4df2babf5ffb83c8ca9d":{"id":"70e745fa514a4df2babf5ffb83c8ca9d","name":"search_again","label":"Search Again","varType":"boolean","secure":false,"category":"vaInputs","nodeId":"e9a32156b0744adc97667ef33b6ad88e","isHidden":false},"fd68d2d2d17b43cf8e736be532f5c5e7":{"id":"fd68d2d2d17b43cf8e736be532f5c5e7","name":"new_when_needed_date","label":"New When Needed Date","varType":"date_time","secure":false,"category":"vaInputs","mode":"date_time","nodeId":"95f0e2c283f44b7fa5779cbf423d1095","isHidden":false},"3a3e0924a250451882cd5ef65b46041b":{"id":"3a3e0924a250451882cd5ef65b46041b","name":"change_when_needed_date","label":"Change When Needed Date","varType":"reference","table":"","inactive":true,"category":"vaInputs","nodeId":"c6cb68c734c745dcb4d6edc79635c06b","isHidden":false},"96715a3553c849db8769caa4a711578e":{"id":"96715a3553c849db8769caa4a711578e","name":"what_to_update","label":"What To Update","varType":"choice","choices":[{"label":"when needed","value":"when needed"},{"label":"short description","value":"short description"},{"label":"nothing","value":"nothing","checked":true,"meta":{}}],"category":"vaInputs","nodeId":"b5b7023ab32b4897898ad1565b7056e1","isHidden":false},"e5d89b606a294529acd1ebc847a2b67f":{"id":"e5d89b606a294529acd1ebc847a2b67f","name":"new_short_description","label":"New Short Description","varType":"string","secure":false,"category":"vaInputs","encryptionHashFunction":"SHA-256","encryptionSalt":{"value":"MTczMjA4ODY5OTUwMCBWQSBEZXNpZ25lciBpcyBhd2Vzb21l","mode":"simple"},"nodeId":"758d7f9bd3314af599ba1d240c352d7c","isHidden":false},"20b2f23b04334809a606c1d693ca4f2b":{"id":"20b2f23b04334809a606c1d693ca4f2b","name":"change_short_description","label":"Change Short Description","varType":"reference","table":"","inactive":true,"category":"vaInputs","nodeId":"6284b2d33f444c2b9e02cda3582a466d","isHidden":false}},"goals":{"primary":{"id":"primary","trigger":{"type":"primary"},"name":"primary","applicability":"","description":"","nodes":{"39f095b4f6724a0785423beaced2f6c7":{"id":"39f095b4f6724a0785423beaced2f6c7","stepType":"Start","name":"Start","greetingResponse":{"value":[{"type":"paragraph","children":[{"text":"I can help you find and update NeedIt records for a type of request."}]}],"mode":"simple"}},"8204c88411fb474aa6f4265e4f0a9669":{"id":"8204c88411fb474aa6f4265e4f0a9669","stepType":"TerminateGoal","name":"End","confirmationMessage":{"value":[{"type":"paragraph","children":[{"text":"Ask again when you need to update other NeedIt records."}]}],"mode":"simple"}},"a1513f4fd70c45d698a72c5f3fc60460":{"name":"NeedIt Type","prompt":{"value":[{"type":"paragraph","children":[{"text":"Which type if NeedIt record would you like to view?"}]}],"mode":"simple"},"confirmMessage":{"value":"","mode":"simple"},"acknowledgeMsg":{"value":"","mode":"simple"},"applicability":{"value":"","mode":"query"},"skippable":{"value":"","mode":"query"},"skipReprompt":{"value":"","mode":"query"},"defaultValue":{"value":"","mode":"simple"},"variableId":"207fa3bea5a344e2a2e017410c3da0fa","detailDescription":"","id":"a1513f4fd70c45d698a72c5f3fc60460","stepType":"ChoicePrompt","hasCardHeader":false,"cardMetadata":{"mode":"card","metadataScript":"","cardTemplate":"","cardFields":{},"cardDefinition":{}},"withNluUserInput":false,"skipIfFulfilled":false},"ed4140b3e4464d9d98ed2a25056114d7":{"id":"ed4140b3e4464d9d98ed2a25056114d7","stepType":"TextOutput","name":"Confirm NeedIt Type","secure":false,"value":[{"value":[{"type":"paragraph","children":[{"text":"You selected: "},{"type":"datapill","dataPill":{"value":"{{vaInputs.needit_type}}","displayValue":"Input Variables➛NeedIt Type"},"children":[{"text":""}]},{"text":""}]}],"mode":"simple","_key":"ff9653bb8c3f466c983896143a62d3f7"}],"requestFeedback":true,"applicability":{"value":"","mode":"query"}},"216922dd23554c5eb41bba0ccc87a593":{"name":"NeedIt List","prompt":{"value":[{"type":"paragraph","children":[{"text":"Select a NeedIt record to view."}]}],"mode":"simple"},"confirmMessage":{"value":"","mode":"simple"},"acknowledgeMsg":{"value":"","mode":"simple"},"applicability":{"value":"","mode":"query"},"skippable":{"value":"","mode":"query"},"skipReprompt":{"value":"","mode":"query"},"defaultValue":{"value":"","mode":"simple"},"variableId":"6f8c634cd0fb45f180a0b830a3956a69","detailDescription":"","id":"216922dd23554c5eb41bba0ccc87a593","stepType":"ReferenceChoicePrompt","mode":"glide_record","script":"","metadataScript":"","cardData":{},"isMultipleSelect":false,"noRecordsResponseMsg":{"value":[{"type":"paragraph","children":[{"text":"You have no open NeedIt records.test gf"}]}],"mode":"simple"},"condition":{"mode":"glide_query","value":"active=true^u_request_type={{vaInputs.needit_type}}^u_requested_for={{vaInputs.user}}"},"hasCardHeader":false,"cardMetadata":{"mode":"card","metadataScript":"","cardTemplate":"","cardFields":{},"cardDefinition":{}},"withNluUserInput":false,"skipIfFulfilled":false},"f1b89427f3514d6e9fbf96e4e776251a":{"id":"f1b89427f3514d6e9fbf96e4e776251a","stepType":"RecordOutput","name":"Need Card","variableId":"6f8c634cd0fb45f180a0b830a3956a69","cardTemplate":"General","cardFields":{},"mode":"variable","tableName":"x_58872_needit_needit","fields":["short_description","u_when_needed","u_requested_for","u_request_type","priority"],"cardDefinition":{"name":"Record","value":"General"},"requestFeedback":true,"applicability":{"value":"","mode":"query"},"condition":{"mode":"glide_query","value":""}},"e9a32156b0744adc97667ef33b6ad88e":{"id":"e9a32156b0744adc97667ef33b6ad88e","stepType":"BooleanPrompt","name":"Search Again","prompt":{"value":[{"type":"paragraph","children":[{"text":"Would you like to view another NeedIt Record?"}]}],"mode":"simple"},"confirmMessage":{"value":"","mode":"simple"},"acknowledgeMsg":{"value":"","mode":"simple"},"applicability":{"value":"","mode":"query"},"skippable":{"value":"","mode":"query"},"skipReprompt":{"value":"","mode":"query"},"defaultValue":{"value":"","mode":"simple"},"withNluUserInput":false,"skipIfFulfilled":false,"variableId":"70e745fa514a4df2babf5ffb83c8ca9d","detailDescription":""},"e2bab10cd18d4cde92eeda8342345947":{"id":"e2bab10cd18d4cde92eeda8342345947","stepType":"Decision","name":"Find more NeedIt Records?"},"95f0e2c283f44b7fa5779cbf423d1095":{"id":"95f0e2c283f44b7fa5779cbf423d1095","stepType":"DateTimePrompt","name":"New When Needed Date","prompt":{"value":[{"type":"paragraph","children":[{"text":"When do you need the NeedIt completed?"}]}],"mode":"simple"},"confirmMessage":{"value":"","mode":"simple"},"acknowledgeMsg":{"value":"","mode":"simple"},"applicability":{"value":"","mode":"query"},"skippable":{"value":"","mode":"query"},"skipReprompt":{"value":"","mode":"query"},"defaultValue":{"value":"","mode":"simple"},"withNluUserInput":false,"skipIfFulfilled":false,"variableId":"fd68d2d2d17b43cf8e736be532f5c5e7","detailDescription":""},"c6cb68c734c745dcb4d6edc79635c06b":{"id":"c6cb68c734c745dcb4d6edc79635c06b","stepType":"CrudAction","name":"Change When Needed Date","template":{"query":{"terms":[{"prefix":"","operator":"=","operand":"u_when_needed","expression":"{{vaInputs.new_when_needed_date}}"}]},"queryString":"u_when_needed={{vaInputs.new_when_needed_date}}"},"mode":"update","record":"6f8c634cd0fb45f180a0b830a3956a69","applicability":{"value":"","mode":"query"},"attachments":[{"value":"","mode":"simple"}],"variableId":"3a3e0924a250451882cd5ef65b46041b"},"6f4194845229447497a7d02e1ccb5ab5":{"id":"6f4194845229447497a7d02e1ccb5ab5","stepType":"RecordOutput","name":"updated Card","variableId":"6f8c634cd0fb45f180a0b830a3956a69","cardTemplate":"General","cardFields":{},"mode":"variable","tableName":"x_58872_needit_needit","fields":["short_description","u_when_needed","u_requested_for","u_request_type","priority"],"cardDefinition":{"name":"Record","value":"General"},"requestFeedback":true,"applicability":{"value":"","mode":"query"},"condition":{"mode":"glide_query","value":""}},"b5b7023ab32b4897898ad1565b7056e1":{"name":"What To Update","prompt":{"value":[{"type":"paragraph","children":[{"text":"What to update？"}]}],"mode":"simple"},"confirmMessage":{"value":"","mode":"simple"},"acknowledgeMsg":{"value":"","mode":"simple"},"applicability":{"value":"","mode":"query"},"skippable":{"value":"","mode":"query"},"skipReprompt":{"value":"","mode":"query"},"defaultValue":{"value":"","mode":"simple"},"variableId":"96715a3553c849db8769caa4a711578e","detailDescription":"","id":"b5b7023ab32b4897898ad1565b7056e1","stepType":"ChoicePrompt","hasCardHeader":false,"cardMetadata":{"mode":"card","metadataScript":"","cardTemplate":"","cardFields":{},"cardDefinition":{}},"withNluUserInput":false,"skipIfFulfilled":false},"5ffab96172744350bb173af23683e081":{"id":"5ffab96172744350bb173af23683e081","stepType":"Decision","name":"Update Field"},"758d7f9bd3314af599ba1d240c352d7c":{"id":"758d7f9bd3314af599ba1d240c352d7c","stepType":"TextPrompt","name":"New short description","prompt":{"value":[{"type":"paragraph","children":[{"text":"What is short description?"}]}],"mode":"simple"},"confirmMessage":{"value":"","mode":"simple"},"acknowledgeMsg":{"value":"","mode":"simple"},"applicability":{"value":"","mode":"query"},"skippable":{"value":"","mode":"query"},"skipReprompt":{"value":"","mode":"query"},"defaultValue":{"value":"","mode":"simple"},"withNluUserInput":false,"skipIfFulfilled":false,"variableId":"e5d89b606a294529acd1ebc847a2b67f","detailDescription":"","inputType":{"format":"Text","script":""},"requestFeedback":true},"6284b2d33f444c2b9e02cda3582a466d":{"id":"6284b2d33f444c2b9e02cda3582a466d","stepType":"CrudAction","name":"Change short description","template":{"query":{"terms":[{"prefix":"","operator":"=","operand":"short_description","expression":"{{vaInputs.new_short_description}}","deserializedExpression":[{"type":"paragraph","children":[{"text":""},{"type":"datapill","dataPill":{"value":"{{vaInputs.new_short_description}}","displayValue":"Input Variables➛New Short Description"},"children":[{"text":""}]},{"text":""}]}]}]},"queryString":"short_description={{vaInputs.new_short_description}}"},"mode":"update","record":"6f8c634cd0fb45f180a0b830a3956a69","applicability":{"value":"","mode":"query"},"attachments":[{"value":"","mode":"simple"}],"variableId":"20b2f23b04334809a606c1d693ca4f2b"}},"edges":[{"id":"a602b71a1c69436eb0b9e33ddc300d42","edgeType":"Edge","source":"ed4140b3e4464d9d98ed2a25056114d7","target":"216922dd23554c5eb41bba0ccc87a593","sourcePort":"","targetPort":""},{"id":"68efc298fbdf4c1086a634d77c21fe8d","edgeType":"Edge","source":"39f095b4f6724a0785423beaced2f6c7","target":"a1513f4fd70c45d698a72c5f3fc60460","sourcePort":"","targetPort":""},{"id":"9845365217064e01a8bd84ca1acc2b94","edgeType":"Edge","source":"a1513f4fd70c45d698a72c5f3fc60460","target":"ed4140b3e4464d9d98ed2a25056114d7","sourcePort":"","targetPort":""},{"id":"b7d0629887a24cbb8944e7f0b603521b","edgeType":"Edge","source":"216922dd23554c5eb41bba0ccc87a593","target":"f1b89427f3514d6e9fbf96e4e776251a","sourcePort":"","targetPort":""},{"id":"29f31b4cdb234c1992e1ee955834b675","edgeType":"Edge","source":"e9a32156b0744adc97667ef33b6ad88e","target":"e2bab10cd18d4cde92eeda8342345947","sourcePort":"","targetPort":""},{"id":"9566fbedb9f848adb74d55578bc830bc","edgeType":"Branch","source":"e2bab10cd18d4cde92eeda8342345947","target":"8204c88411fb474aa6f4265e4f0a9669","sourcePort":"","targetPort":"","expression":{"value":"vaInputs.search_again=","mode":"query"},"label":"No"},{"id":"f81a2bcdea8a4a1c8c68ab22a6149584","edgeType":"Branch","source":"e2bab10cd18d4cde92eeda8342345947","target":"a1513f4fd70c45d698a72c5f3fc60460","sourcePort":"","targetPort":"","expression":{"value":"vaInputs.search_again=true","mode":"query"},"label":"Yes"},{"id":"83f4101ed5774ea6bc79f316ebfcb4da","edgeType":"Edge","source":"95f0e2c283f44b7fa5779cbf423d1095","target":"c6cb68c734c745dcb4d6edc79635c06b","sourcePort":"","targetPort":""},{"id":"51e3908d64a74a298367fd4489e432c4","edgeType":"Edge","source":"c6cb68c734c745dcb4d6edc79635c06b","target":"6f4194845229447497a7d02e1ccb5ab5","sourcePort":"","targetPort":""},{"id":"cec953f0252c458183f3ab482377e36d","edgeType":"Edge","source":"6f4194845229447497a7d02e1ccb5ab5","target":"e9a32156b0744adc97667ef33b6ad88e","sourcePort":"","targetPort":""},{"id":"069ae01e11a34b18814b46776a9904b9","edgeType":"Edge","source":"f1b89427f3514d6e9fbf96e4e776251a","target":"b5b7023ab32b4897898ad1565b7056e1","sourcePort":"","targetPort":""},{"id":"c50f477cdf724e7da82877581dee3898","edgeType":"Edge","source":"b5b7023ab32b4897898ad1565b7056e1","target":"5ffab96172744350bb173af23683e081","sourcePort":"","targetPort":""},{"id":"10ab15215b654c918d452ce12e4d6f22","edgeType":"Branch","source":"5ffab96172744350bb173af23683e081","target":"95f0e2c283f44b7fa5779cbf423d1095","sourcePort":"","targetPort":"","expression":{"value":"vaInputs.what_to_update=when needed","mode":"query"},"label":"update When needed"},{"id":"f51553a0be654346bca42d2f40edede2","edgeType":"Branch","source":"5ffab96172744350bb173af23683e081","target":"e9a32156b0744adc97667ef33b6ad88e","sourcePort":"","targetPort":"","expression":{"value":"vaInputs.what_to_update=nothing","mode":"query"},"label":"Always"},{"id":"4eb3440acf554c538ab6ae8b868c7dfa","edgeType":"Branch","source":"5ffab96172744350bb173af23683e081","target":"758d7f9bd3314af599ba1d240c352d7c","sourcePort":"","targetPort":"","expression":{"value":"vaInputs.what_to_update=short description","mode":"query"},"label":"update short discription"},{"id":"4fa6ae45e1e1490a9672c56bbf8c6e1b","edgeType":"Edge","source":"758d7f9bd3314af599ba1d240c352d7c","target":"6284b2d33f444c2b9e02cda3582a466d","sourcePort":"","targetPort":""},{"id":"1e5bfd21fa0742bfa3c383cb4b20dd44","edgeType":"Edge","source":"6284b2d33f444c2b9e02cda3582a466d","target":"6f4194845229447497a7d02e1ccb5ab5","sourcePort":"","targetPort":""}]}}}</graph>
        <key_phrases>Update NeedIt Records bak,Update NeedIt Records</key_phrases>
        <library>false</library>
        <live_agent>false</live_agent>
        <model_type>nlu_keyword</model_type>
        <modify_confirmation_enabled>false</modify_confirmation_enabled>
        <name>Update NeedIt Records bak</name>
        <nlu_intent/>
        <nlu_intent_label/>
        <nlu_model/>
        <nlu_model_label/>
        <nlu_provider/>
        <palette_label/>
        <roles/>
        <root_topic_id>f83a7c2c53c21210102d50b0a0490e39</root_topic_id>
        <secure_custom_input_control>false</secure_custom_input_control>
        <source_topic_id>f83a7c2c53c21210102d50b0a0490e39</source_topic_id>
        <sys_class_name>sys_cb_topic</sys_class_name>
        <sys_created_by>admin</sys_created_by>
        <sys_created_on>2024-11-20 08:09:54</sys_created_on>
        <sys_domain>global</sys_domain>
        <sys_id>58df6d64530a1210102d50b0a0490e57</sys_id>
        <sys_mod_count>0</sys_mod_count>
        <sys_name>Update NeedIt Records bak</sys_name>
        <sys_package display_value="NeedIt" source="x_58872_needit">6ead8e780f603200cd674f8ce1050ed1</sys_package>
        <sys_policy/>
        <sys_scope display_value="NeedIt">6ead8e780f603200cd674f8ce1050ed1</sys_scope>
        <sys_update_name>sys_cb_topic_58df6d64530a1210102d50b0a0490e57</sys_update_name>
        <sys_updated_by>admin</sys_updated_by>
        <sys_updated_on>2024-11-20 08:09:54</sys_updated_on>
        <title>Update NeedIt Records bak</title>
        <triggerable_by_notification>false</triggerable_by_notification>
        <type>STANDARD</type>
    </sys_cb_topic>
    <sys_translated_text action="DELETE" query="documentkey=58df6d64530a1210102d50b0a0490e57"/>
    <sys_update_version action="INSERT_OR_UPDATE">
        <action>DELETE</action>
        <application display_value="NeedIt">6ead8e780f603200cd674f8ce1050ed1</application>
        <file_path/>
        <instance_id>bf6dbb1fdbea395438f117291396196c</instance_id>
        <instance_name>dev220951</instance_name>
        <name>sys_cb_topic_58df6d64530a1210102d50b0a0490e57</name>
        <payload><![CDATA[<?xml version="1.0" encoding="UTF-8"?><record_update sys_domain="global" table="sys_cb_topic"><sys_cb_topic action="INSERT_OR_UPDATE"><applicability/><applicability_mode>query</applicability_mode><autopilot_topic>false</autopilot_topic><category/><channels/><connect_queue/><context_profiles/><description/><dialog_acts_enabled>false</dialog_acts_enabled><expose_on_palette>false</expose_on_palette><flexible_conversation_switching>false</flexible_conversation_switching><foundational>false</foundational><graph>{"graph_api_version":"1.0.68","variables":{"12a34d5f07964f90b41659dde94a41c6":{"category":"vaInputs","id":"12a34d5f07964f90b41659dde94a41c6","label":"User","name":"user","table":"sys_user","varType":"reference"},"207fa3bea5a344e2a2e017410c3da0fa":{"id":"207fa3bea5a344e2a2e017410c3da0fa","name":"needit_type","label":"NeedIt Type","varType":"choice","choices":[{"label":"legal","value":"legal"},{"label":"Facilities","value":"Facilities"},{"label":"Human Resources","value":"Human Resources","checked":true,"meta":{}}],"category":"vaInputs","nodeId":"a1513f4fd70c45d698a72c5f3fc60460","isHidden":false},"6f8c634cd0fb45f180a0b830a3956a69":{"id":"6f8c634cd0fb45f180a0b830a3956a69","name":"needit_list","label":"NeedIt List","varType":"reference","table":"x_58872_needit_needit","category":"vaInputs","nodeId":"6f4194845229447497a7d02e1ccb5ab5","isHidden":false},"70e745fa514a4df2babf5ffb83c8ca9d":{"id":"70e745fa514a4df2babf5ffb83c8ca9d","name":"search_again","label":"Search Again","varType":"boolean","secure":false,"category":"vaInputs","nodeId":"e9a32156b0744adc97667ef33b6ad88e","isHidden":false},"fd68d2d2d17b43cf8e736be532f5c5e7":{"id":"fd68d2d2d17b43cf8e736be532f5c5e7","name":"new_when_needed_date","label":"New When Needed Date","varType":"date_time","secure":false,"category":"vaInputs","mode":"date_time","nodeId":"95f0e2c283f44b7fa5779cbf423d1095","isHidden":false},"3a3e0924a250451882cd5ef65b46041b":{"id":"3a3e0924a250451882cd5ef65b46041b","name":"change_when_needed_date","label":"Change When Needed Date","varType":"reference","table":"","inactive":true,"category":"vaInputs","nodeId":"c6cb68c734c745dcb4d6edc79635c06b","isHidden":false},"96715a3553c849db8769caa4a711578e":{"id":"96715a3553c849db8769caa4a711578e","name":"what_to_update","label":"What To Update","varType":"choice","choices":[{"label":"when needed","value":"when needed"},{"label":"short description","value":"short description"},{"label":"nothing","value":"nothing","checked":true,"meta":{}}],"category":"vaInputs","nodeId":"b5b7023ab32b4897898ad1565b7056e1","isHidden":false},"e5d89b606a294529acd1ebc847a2b67f":{"id":"e5d89b606a294529acd1ebc847a2b67f","name":"new_short_description","label":"New Short Description","varType":"string","secure":false,"category":"vaInputs","encryptionHashFunction":"SHA-256","encryptionSalt":{"value":"MTczMjA4ODY5OTUwMCBWQSBEZXNpZ25lciBpcyBhd2Vzb21l","mode":"simple"},"nodeId":"758d7f9bd3314af599ba1d240c352d7c","isHidden":false},"20b2f23b04334809a606c1d693ca4f2b":{"id":"20b2f23b04334809a606c1d693ca4f2b","name":"change_short_description","label":"Change Short Description","varType":"reference","table":"","inactive":true,"category":"vaInputs","nodeId":"6284b2d33f444c2b9e02cda3582a466d","isHidden":false}},"goals":{"primary":{"id":"primary","trigger":{"type":"primary"},"name":"primary","applicability":"","description":"","nodes":{"39f095b4f6724a0785423beaced2f6c7":{"id":"39f095b4f6724a0785423beaced2f6c7","stepType":"Start","name":"Start","greetingResponse":{"value":[{"type":"paragraph","children":[{"text":"I can help you find and update NeedIt records for a type of request."}]}],"mode":"simple"}},"8204c88411fb474aa6f4265e4f0a9669":{"id":"8204c88411fb474aa6f4265e4f0a9669","stepType":"TerminateGoal","name":"End","confirmationMessage":{"value":[{"type":"paragraph","children":[{"text":"Ask again when you need to update other NeedIt records."}]}],"mode":"simple"}},"a1513f4fd70c45d698a72c5f3fc60460":{"name":"NeedIt Type","prompt":{"value":[{"type":"paragraph","children":[{"text":"Which type if NeedIt record would you like to view?"}]}],"mode":"simple"},"confirmMessage":{"value":"","mode":"simple"},"acknowledgeMsg":{"value":"","mode":"simple"},"applicability":{"value":"","mode":"query"},"skippable":{"value":"","mode":"query"},"skipReprompt":{"value":"","mode":"query"},"defaultValue":{"value":"","mode":"simple"},"variableId":"207fa3bea5a344e2a2e017410c3da0fa","detailDescription":"","id":"a1513f4fd70c45d698a72c5f3fc60460","stepType":"ChoicePrompt","hasCardHeader":false,"cardMetadata":{"mode":"card","metadataScript":"","cardTemplate":"","cardFields":{},"cardDefinition":{}},"withNluUserInput":false,"skipIfFulfilled":false},"ed4140b3e4464d9d98ed2a25056114d7":{"id":"ed4140b3e4464d9d98ed2a25056114d7","stepType":"TextOutput","name":"Confirm NeedIt Type","secure":false,"value":[{"value":[{"type":"paragraph","children":[{"text":"You selected: "},{"type":"datapill","dataPill":{"value":"{{vaInputs.needit_type}}","displayValue":"Input Variables➛NeedIt Type"},"children":[{"text":""}]},{"text":""}]}],"mode":"simple","_key":"ff9653bb8c3f466c983896143a62d3f7"}],"requestFeedback":true,"applicability":{"value":"","mode":"query"}},"216922dd23554c5eb41bba0ccc87a593":{"name":"NeedIt List","prompt":{"value":[{"type":"paragraph","children":[{"text":"Select a NeedIt record to view."}]}],"mode":"simple"},"confirmMessage":{"value":"","mode":"simple"},"acknowledgeMsg":{"value":"","mode":"simple"},"applicability":{"value":"","mode":"query"},"skippable":{"value":"","mode":"query"},"skipReprompt":{"value":"","mode":"query"},"defaultValue":{"value":"","mode":"simple"},"variableId":"6f8c634cd0fb45f180a0b830a3956a69","detailDescription":"","id":"216922dd23554c5eb41bba0ccc87a593","stepType":"ReferenceChoicePrompt","mode":"glide_record","script":"","metadataScript":"","cardData":{},"isMultipleSelect":false,"noRecordsResponseMsg":{"value":[{"type":"paragraph","children":[{"text":"You have no open NeedIt records.test gf"}]}],"mode":"simple"},"condition":{"mode":"glide_query","value":"active=true^u_request_type={{vaInputs.needit_type}}^u_requested_for={{vaInputs.user}}"},"hasCardHeader":false,"cardMetadata":{"mode":"card","metadataScript":"","cardTemplate":"","cardFields":{},"cardDefinition":{}},"withNluUserInput":false,"skipIfFulfilled":false},"f1b89427f3514d6e9fbf96e4e776251a":{"id":"f1b89427f3514d6e9fbf96e4e776251a","stepType":"RecordOutput","name":"Need Card","variableId":"6f8c634cd0fb45f180a0b830a3956a69","cardTemplate":"General","cardFields":{},"mode":"variable","tableName":"x_58872_needit_needit","fields":["short_description","u_when_needed","u_requested_for","u_request_type","priority"],"cardDefinition":{"name":"Record","value":"General"},"requestFeedback":true,"applicability":{"value":"","mode":"query"},"condition":{"mode":"glide_query","value":""}},"e9a32156b0744adc97667ef33b6ad88e":{"id":"e9a32156b0744adc97667ef33b6ad88e","stepType":"BooleanPrompt","name":"Search Again","prompt":{"value":[{"type":"paragraph","children":[{"text":"Would you like to view another NeedIt Record?"}]}],"mode":"simple"},"confirmMessage":{"value":"","mode":"simple"},"acknowledgeMsg":{"value":"","mode":"simple"},"applicability":{"value":"","mode":"query"},"skippable":{"value":"","mode":"query"},"skipReprompt":{"value":"","mode":"query"},"defaultValue":{"value":"","mode":"simple"},"withNluUserInput":false,"skipIfFulfilled":false,"variableId":"70e745fa514a4df2babf5ffb83c8ca9d","detailDescription":""},"e2bab10cd18d4cde92eeda8342345947":{"id":"e2bab10cd18d4cde92eeda8342345947","stepType":"Decision","name":"Find more NeedIt Records?"},"95f0e2c283f44b7fa5779cbf423d1095":{"id":"95f0e2c283f44b7fa5779cbf423d1095","stepType":"DateTimePrompt","name":"New When Needed Date","prompt":{"value":[{"type":"paragraph","children":[{"text":"When do you need the NeedIt completed?"}]}],"mode":"simple"},"confirmMessage":{"value":"","mode":"simple"},"acknowledgeMsg":{"value":"","mode":"simple"},"applicability":{"value":"","mode":"query"},"skippable":{"value":"","mode":"query"},"skipReprompt":{"value":"","mode":"query"},"defaultValue":{"value":"","mode":"simple"},"withNluUserInput":false,"skipIfFulfilled":false,"variableId":"fd68d2d2d17b43cf8e736be532f5c5e7","detailDescription":""},"c6cb68c734c745dcb4d6edc79635c06b":{"id":"c6cb68c734c745dcb4d6edc79635c06b","stepType":"CrudAction","name":"Change When Needed Date","template":{"query":{"terms":[{"prefix":"","operator":"=","operand":"u_when_needed","expression":"{{vaInputs.new_when_needed_date}}"}]},"queryString":"u_when_needed={{vaInputs.new_when_needed_date}}"},"mode":"update","record":"6f8c634cd0fb45f180a0b830a3956a69","applicability":{"value":"","mode":"query"},"attachments":[{"value":"","mode":"simple"}],"variableId":"3a3e0924a250451882cd5ef65b46041b"},"6f4194845229447497a7d02e1ccb5ab5":{"id":"6f4194845229447497a7d02e1ccb5ab5","stepType":"RecordOutput","name":"updated Card","variableId":"6f8c634cd0fb45f180a0b830a3956a69","cardTemplate":"General","cardFields":{},"mode":"variable","tableName":"x_58872_needit_needit","fields":["short_description","u_when_needed","u_requested_for","u_request_type","priority"],"cardDefinition":{"name":"Record","value":"General"},"requestFeedback":true,"applicability":{"value":"","mode":"query"},"condition":{"mode":"glide_query","value":""}},"b5b7023ab32b4897898ad1565b7056e1":{"name":"What To Update","prompt":{"value":[{"type":"paragraph","children":[{"text":"What to update？"}]}],"mode":"simple"},"confirmMessage":{"value":"","mode":"simple"},"acknowledgeMsg":{"value":"","mode":"simple"},"applicability":{"value":"","mode":"query"},"skippable":{"value":"","mode":"query"},"skipReprompt":{"value":"","mode":"query"},"defaultValue":{"value":"","mode":"simple"},"variableId":"96715a3553c849db8769caa4a711578e","detailDescription":"","id":"b5b7023ab32b4897898ad1565b7056e1","stepType":"ChoicePrompt","hasCardHeader":false,"cardMetadata":{"mode":"card","metadataScript":"","cardTemplate":"","cardFields":{},"cardDefinition":{}},"withNluUserInput":false,"skipIfFulfilled":false},"5ffab96172744350bb173af23683e081":{"id":"5ffab96172744350bb173af23683e081","stepType":"Decision","name":"Update Field"},"758d7f9bd3314af599ba1d240c352d7c":{"id":"758d7f9bd3314af599ba1d240c352d7c","stepType":"TextPrompt","name":"New short description","prompt":{"value":[{"type":"paragraph","children":[{"text":"What is short description?"}]}],"mode":"simple"},"confirmMessage":{"value":"","mode":"simple"},"acknowledgeMsg":{"value":"","mode":"simple"},"applicability":{"value":"","mode":"query"},"skippable":{"value":"","mode":"query"},"skipReprompt":{"value":"","mode":"query"},"defaultValue":{"value":"","mode":"simple"},"withNluUserInput":false,"skipIfFulfilled":false,"variableId":"e5d89b606a294529acd1ebc847a2b67f","detailDescription":"","inputType":{"format":"Text","script":""},"requestFeedback":true},"6284b2d33f444c2b9e02cda3582a466d":{"id":"6284b2d33f444c2b9e02cda3582a466d","stepType":"CrudAction","name":"Change short description","template":{"query":{"terms":[{"prefix":"","operator":"=","operand":"short_description","expression":"{{vaInputs.new_short_description}}","deserializedExpression":[{"type":"paragraph","children":[{"text":""},{"type":"datapill","dataPill":{"value":"{{vaInputs.new_short_description}}","displayValue":"Input Variables➛New Short Description"},"children":[{"text":""}]},{"text":""}]}]}]},"queryString":"short_description={{vaInputs.new_short_description}}"},"mode":"update","record":"6f8c634cd0fb45f180a0b830a3956a69","applicability":{"value":"","mode":"query"},"attachments":[{"value":"","mode":"simple"}],"variableId":"20b2f23b04334809a606c1d693ca4f2b"}},"edges":[{"id":"a602b71a1c69436eb0b9e33ddc300d42","edgeType":"Edge","source":"ed4140b3e4464d9d98ed2a25056114d7","target":"216922dd23554c5eb41bba0ccc87a593","sourcePort":"","targetPort":""},{"id":"68efc298fbdf4c1086a634d77c21fe8d","edgeType":"Edge","source":"39f095b4f6724a0785423beaced2f6c7","target":"a1513f4fd70c45d698a72c5f3fc60460","sourcePort":"","targetPort":""},{"id":"9845365217064e01a8bd84ca1acc2b94","edgeType":"Edge","source":"a1513f4fd70c45d698a72c5f3fc60460","target":"ed4140b3e4464d9d98ed2a25056114d7","sourcePort":"","targetPort":""},{"id":"b7d0629887a24cbb8944e7f0b603521b","edgeType":"Edge","source":"216922dd23554c5eb41bba0ccc87a593","target":"f1b89427f3514d6e9fbf96e4e776251a","sourcePort":"","targetPort":""},{"id":"29f31b4cdb234c1992e1ee955834b675","edgeType":"Edge","source":"e9a32156b0744adc97667ef33b6ad88e","target":"e2bab10cd18d4cde92eeda8342345947","sourcePort":"","targetPort":""},{"id":"9566fbedb9f848adb74d55578bc830bc","edgeType":"Branch","source":"e2bab10cd18d4cde92eeda8342345947","target":"8204c88411fb474aa6f4265e4f0a9669","sourcePort":"","targetPort":"","expression":{"value":"vaInputs.search_again=","mode":"query"},"label":"No"},{"id":"f81a2bcdea8a4a1c8c68ab22a6149584","edgeType":"Branch","source":"e2bab10cd18d4cde92eeda8342345947","target":"a1513f4fd70c45d698a72c5f3fc60460","sourcePort":"","targetPort":"","expression":{"value":"vaInputs.search_again=true","mode":"query"},"label":"Yes"},{"id":"83f4101ed5774ea6bc79f316ebfcb4da","edgeType":"Edge","source":"95f0e2c283f44b7fa5779cbf423d1095","target":"c6cb68c734c745dcb4d6edc79635c06b","sourcePort":"","targetPort":""},{"id":"51e3908d64a74a298367fd4489e432c4","edgeType":"Edge","source":"c6cb68c734c745dcb4d6edc79635c06b","target":"6f4194845229447497a7d02e1ccb5ab5","sourcePort":"","targetPort":""},{"id":"cec953f0252c458183f3ab482377e36d","edgeType":"Edge","source":"6f4194845229447497a7d02e1ccb5ab5","target":"e9a32156b0744adc97667ef33b6ad88e","sourcePort":"","targetPort":""},{"id":"069ae01e11a34b18814b46776a9904b9","edgeType":"Edge","source":"f1b89427f3514d6e9fbf96e4e776251a","target":"b5b7023ab32b4897898ad1565b7056e1","sourcePort":"","targetPort":""},{"id":"c50f477cdf724e7da82877581dee3898","edgeType":"Edge","source":"b5b7023ab32b4897898ad1565b7056e1","target":"5ffab96172744350bb173af23683e081","sourcePort":"","targetPort":""},{"id":"10ab15215b654c918d452ce12e4d6f22","edgeType":"Branch","source":"5ffab96172744350bb173af23683e081","target":"95f0e2c283f44b7fa5779cbf423d1095","sourcePort":"","targetPort":"","expression":{"value":"vaInputs.what_to_update=when needed","mode":"query"},"label":"update When needed"},{"id":"f51553a0be654346bca42d2f40edede2","edgeType":"Branch","source":"5ffab96172744350bb173af23683e081","target":"e9a32156b0744adc97667ef33b6ad88e","sourcePort":"","targetPort":"","expression":{"value":"vaInputs.what_to_update=nothing","mode":"query"},"label":"Always"},{"id":"4eb3440acf554c538ab6ae8b868c7dfa","edgeType":"Branch","source":"5ffab96172744350bb173af23683e081","target":"758d7f9bd3314af599ba1d240c352d7c","sourcePort":"","targetPort":"","expression":{"value":"vaInputs.what_to_update=short description","mode":"query"},"label":"update short discription"},{"id":"4fa6ae45e1e1490a9672c56bbf8c6e1b","edgeType":"Edge","source":"758d7f9bd3314af599ba1d240c352d7c","target":"6284b2d33f444c2b9e02cda3582a466d","sourcePort":"","targetPort":""},{"id":"1e5bfd21fa0742bfa3c383cb4b20dd44","edgeType":"Edge","source":"6284b2d33f444c2b9e02cda3582a466d","target":"6f4194845229447497a7d02e1ccb5ab5","sourcePort":"","targetPort":""}]}}}</graph><key_phrases>Update NeedIt Records bak,Update NeedIt Records</key_phrases><library>false</library><live_agent>false</live_agent><model_type>nlu_keyword</model_type><modify_confirmation_enabled>false</modify_confirmation_enabled><name>Update NeedIt Records bak</name><nlu_intent/><nlu_intent_label/><nlu_model/><nlu_model_label/><nlu_provider/><palette_label/><roles/><root_topic_id>f83a7c2c53c21210102d50b0a0490e39</root_topic_id><secure_custom_input_control>false</secure_custom_input_control><source_topic_id>f83a7c2c53c21210102d50b0a0490e39</source_topic_id><sys_class_name>sys_cb_topic</sys_class_name><sys_created_by>admin</sys_created_by><sys_created_on>2024-11-20 08:09:54</sys_created_on><sys_domain>global</sys_domain><sys_id>58df6d64530a1210102d50b0a0490e57</sys_id><sys_mod_count>0</sys_mod_count><sys_name>Update NeedIt Records bak</sys_name><sys_package display_value="NeedIt" source="x_58872_needit">6ead8e780f603200cd674f8ce1050ed1</sys_package><sys_policy/><sys_scope display_value="NeedIt">6ead8e780f603200cd674f8ce1050ed1</sys_scope><sys_update_name>sys_cb_topic_58df6d64530a1210102d50b0a0490e57</sys_update_name><sys_updated_by>admin</sys_updated_by><sys_updated_on>2024-11-20 08:09:54</sys_updated_on><title>Update NeedIt Records bak</title><triggerable_by_notification>false</triggerable_by_notification><type>STANDARD</type></sys_cb_topic><sys_translated_text action="delete_multiple" query="documentkey=58df6d64530a1210102d50b0a0490e57"/></record_update>]]></payload>
        <payload_hash>1262823618</payload_hash>
        <record_name>Update NeedIt Records bak</record_name>
        <reverted_from/>
        <source>79b1d11e53751210102d50b0a0490ea8</source>
        <source_table>sys_update_set</source_table>
        <state>previous</state>
        <sys_created_by>admin</sys_created_by>
        <sys_created_on>2024-11-20 08:09:54</sys_created_on>
        <sys_id>d4df6d64530a1210102d50b0a0490e5a</sys_id>
        <sys_mod_count>0</sys_mod_count>
        <sys_recorded_at>193489eeba80000001</sys_recorded_at>
        <sys_updated_by>admin</sys_updated_by>
        <sys_updated_on>2024-11-20 08:09:54</sys_updated_on>
        <type>Topic</type>
        <update_guid>d8df6d64030a1210759575b1e2a97259</update_guid>
        <update_guid_history>d8df6d64030a1210759575b1e2a97259:1262823618</update_guid_history>
    </sys_update_version>
    <sys_metadata_delete action="INSERT_OR_UPDATE">
        <sys_audit_delete/>
        <sys_class_name>sys_metadata_delete</sys_class_name>
        <sys_created_by>admin</sys_created_by>
        <sys_created_on>2024-11-20 09:48:44</sys_created_on>
        <sys_db_object display_value="" name="sys_cb_topic">sys_cb_topic</sys_db_object>
        <sys_id>6b4498b5152f4e03815eaf452dcc4a51</sys_id>
        <sys_metadata>58df6d64530a1210102d50b0a0490e57</sys_metadata>
        <sys_mod_count>0</sys_mod_count>
        <sys_name>Update NeedIt Records bak</sys_name>
        <sys_package display_value="NeedIt" source="x_58872_needit">6ead8e780f603200cd674f8ce1050ed1</sys_package>
        <sys_parent/>
        <sys_policy/>
        <sys_scope display_value="NeedIt">6ead8e780f603200cd674f8ce1050ed1</sys_scope>
        <sys_scope_delete display_value="">94872a8897db403e8ee69a431de2fca4</sys_scope_delete>
        <sys_update_name>sys_cb_topic_58df6d64530a1210102d50b0a0490e57</sys_update_name>
        <sys_update_version display_value="sys_cb_topic_58df6d64530a1210102d50b0a0490e57">d4df6d64530a1210102d50b0a0490e5a</sys_update_version>
        <sys_updated_by>admin</sys_updated_by>
        <sys_updated_on>2024-11-20 09:48:44</sys_updated_on>
    </sys_metadata_delete>
</record_update>
